dual_autodiff_x_bb667-0.0.1b1.dist-info/top_level.txt
dual_autodiff_x_bb667-0.0.1b1.dist-info/WHEEL
dual_autodiff_x_bb667-0.0.1b1.dist-info/METADATA
dual_autodiff_x_bb667-0.0.1b1.dist-info/RECORD
dual_autodiff_x/dual.cpython-39-darwin.so
dual_autodiff_x/dual.c
dual_autodiff_x/autodiff_tools.cpython-39-darwin.so
dual_autodiff_x/__init__.py
dual_autodiff_x/autodiff_tools.cpython-310-x86_64-linux-gnu.so
dual_autodiff_x/autodiff_tools.c
dual_autodiff_x/dual.cpython-310-x86_64-linux-gnu.so
