Metadata-Version: 2.1
Name: dual_autodiff_x_bb667
Version: 0.0.1b1
Summary: A package
